oracle_mcp_server/__init__.py
oracle_mcp_server/oracle_tools.py
oracle_mcp_server-1.0.9.dist-info/METADATA
oracle_mcp_server-1.0.9.dist-info/WHEEL
oracle_mcp_server-1.0.9.dist-info/entry_points.txt
oracle_mcp_server-1.0.9.dist-info/licenses/LICENSE
oracle_mcp_server-1.0.9.dist-info/RECORD
