Metadata-Version: 2.4
Name: oracle-mcp-server
Version: 1.0.9
Summary: Model Context Protocol server to access oracle, supporting Oracle 11g and above.
Author-email: MCP Oracle Server Team <mcp-oracle@example.com>
License-File: LICENSE
Requires-Python: >=3.12
Requires-Dist: mcp[cli]>=1.5.0
Requires-Dist: oracledb>=3.0.0
Requires-Dist: python-dotenv>=1.0.1
